{
    "domain": {
        "name": "RePermit",
        "version": "1",
        "chainId": "<CHAINID>",
        "verifyingContract": "<REPERMIT>"
    },
    "primaryType": "RePermitWitnessTransferFrom",
    "types": {
        "RePermitWitnessTransferFrom": [
            {
                "name": "permitted",
                "type": "TokenPermissions"
            },
            {
                "name": "spender",
                "type": "address"
            },
            {
                "name": "nonce",
                "type": "uint256"
            },
            {
                "name": "deadline",
                "type": "uint256"
            },
            {
                "name": "witness",
                "type": "Order"
            }
        ],
        "Exchange": [
            {
                "name": "adapter",
                "type": "address"
            },
            {
                "name": "ref",
                "type": "address"
            },
            {
                "name": "share",
                "type": "uint32"
            }
        ],
        "Input": [
            {
                "name": "token",
                "type": "address"
            },
            {
                "name": "amount",
                "type": "uint256"
            },
            {
                "name": "maxAmount",
                "type": "uint256"
            }
        ],
        "Order": [
            {
                "name": "info",
                "type": "OrderInfo"
            },
            {
                "name": "executor",
                "type": "address"
            },
            {
                "name": "exchange",
                "type": "Exchange"
            },
            {
                "name": "exclusivity",
                "type": "uint32"
            },
            {
                "name": "epoch",
                "type": "uint32"
            },
            {
                "name": "slippage",
                "type": "uint32"
            },
            {
                "name": "freshness",
                "type": "uint32"
            },
            {
                "name": "input",
                "type": "Input"
            },
            {
                "name": "output",
                "type": "Output"
            }
        ],
        "OrderInfo": [
            {
                "name": "reactor",
                "type": "address"
            },
            {
                "name": "swapper",
                "type": "address"
            },
            {
                "name": "nonce",
                "type": "uint256"
            },
            {
                "name": "deadline",
                "type": "uint256"
            },
            {
                "name": "additionalValidationContract",
                "type": "address"
            },
            {
                "name": "additionalValidationData",
                "type": "bytes"
            }
        ],
        "Output": [
            {
                "name": "token",
                "type": "address"
            },
            {
                "name": "amount",
                "type": "uint256"
            },
            {
                "name": "maxAmount",
                "type": "uint256"
            },
            {
                "name": "recipient",
                "type": "address"
            }
        ],
        "TokenPermissions": [
            {
                "name": "token",
                "type": "address"
            },
            {
                "name": "amount",
                "type": "uint256"
            }
        ]
    },
    "message": {
        "permitted": {
            "token": "<INTOKEN>",
            "amount": "<INTOTALAMOUNT>"
        },
        "spender": "<REACTOR>",
        "nonce": "<NONCE>",
        "deadline": "<DEADLINE>",
        "witness": {
            "info": {
                "reactor": "<REACTOR>",
                "swapper": "<SWAPPER>",
                "nonce": "<NONCE>",
                "deadline": "<DEADLINE>",
                "additionalValidationContract": "<EXECUTOR>",
                "additionalValidationData": "<EXECUTORDATA>"
            },
            "executor": "<EXECUTOR>",
            "exchange": {
                "adapter": "<ADAPTER>",
                "ref": "<REFERRER>",
                "share": "<REFSHAREBPS>"
            },
            "exclusivity": "<EXCLUSIVITYBPS>",
            "epoch": "<EPOCHSECONDS>",
            "slippage": "<SLIPPAGE>",
            "freshness": "<FRESHNESSSECONDS>",
            "input": {
                "token": "<INTOKEN>",
                "amount": "<INCHUNKAMOUNT>",
                "maxAmount": "<INTOTALAMOUNT>"
            },
            "output": {
                "token": "<OUTTOKEN>",
                "amount": "<OUTAMOUNTMIN>",
                "maxAmount": "<OUTAMOUNTTRIGGER>",
                "recipient": "<RECIPIENT>"
            }
        }
    }
}

